{"cameraMode":{"drawMode":0,"name":"Shaded","section":"Shading Mode"},"sceneLighting":true,"audioPlay":false,"sceneViewState":{"m_AlwaysRefresh":false,"showFog":true,"showSkybox":true,"showFlares":true,"showImageEffects":true,"showParticleSystems":true,"showVisualEffectGraphs":true,"m_FxEnabled":true},"in2DMode":false,"pivot":{"x":10.02362060546875,"y":-9.624698638916016,"z":-4.659524917602539},"rotation":{"x":0.08028090745210648,"y":0.9035741686820984,"z":-0.3733287751674652,"w":0.19428998231887818},"size":14.609249114990235,"orthographic":false}